{
  "timestamp": "20250723_134831",
  "job_id": "ad577e73-a745-4e69-8dd6-7c2391a24c3f",
  "has_markdown_block": false,
  "markdown_content_length": 16238,
  "markdown_content_preview": "好的，作為一位專業的強化學習分析顧問，我將根據您提供的訓練數據進行深入分析，並為您生成一份包含學習效果評估、問題診斷、改進建議以及算法分析的綜合報告。報告將同時以 Markdown 和 HTML 兩種格式呈現。\n\n***\n\n## 強化學習訓練分析報告\n\n**報告日期:** 2023年10月27日\n**分析顧問:** 您的專業強化學習分析顧問\n**分析對象:** 基於Q-Table的強化學習智能體訓練過程\n\n### 總體摘要\n\n本次訓練共進行了100個回合，智能體在學習過程中表現出明顯的進步趨勢，平均獎勵和步數均隨訓練推移而上升。智能體成功定位到了一個高獎勵值的區域。然而，深入分析顯示，智能體**未能學會達成最終目標的最優策略**，而是陷入了一個高獎勵的局部最優解（循環陷阱）中，導致回合無法正常終止。儘管獎勵值較高，但目前的模型不具備實用性，需要進一步的調整與優化。\n\n---\n\n### Markdown 版本報告\n\n---\n\n### 1. 學習效果評估\n\n#### 1.1 學習曲線分析\n- **獎勵趨勢 (✅ 正面):** 獎勵的總體趨勢是上升的，平均獎勵達到 `832.57`，最終回合..."
}